texpy/__init__.py
heidtex-0.0.1.dist-info/LICENSE
heidtex-0.0.1.dist-info/METADATA
heidtex-0.0.1.dist-info/WHEEL
heidtex-0.0.1.dist-info/top_level.txt
heidtex-0.0.1.dist-info/RECORD
